[
  {
    "file": "1. Synoligo Spot Bonus Program Guidelines.pdf",
    "title": "1. Synoligo Spot Bonus Program Guidelines",
    "tags": [],
    "notes": ""
  },
  {
    "file": "2. Spot Bonus Nomination Form.docx",
    "title": "2. Spot Bonus Nomination Form",
    "tags": [],
    "notes": ""
  },
  {
    "file": "20231219_Synoligo Biotechnologies Inc - BENEFIT HIGHLIGHT SHEET - 1.pdf",
    "title": "20231219 Synoligo Biotechnologies Inc BENEFIT HIGHLIGHT SHEET 1",
    "tags": [],
    "notes": ""
  },
  {
    "file": "22-088_EEOC_KnowYourRights6.12ScreenRdr.pdf",
    "title": "22 088 EEOC KnowYourRights6.12ScreenRdr",
    "tags": [],
    "notes": ""
  },
  {
    "file": "3. Synoligo Spot Bonus PPT.pptx",
    "title": "3. Synoligo Spot Bonus PPT",
    "tags": [],
    "notes": ""
  },
  {
    "file": "Aetna Enrollment Guide_2025 (1).pdf",
    "title": "Aetna Enrollment Guide 2025 (1)",
    "tags": [],
    "notes": ""
  },
  {
    "file": "ANG HDHP 8000 8000 SOB.pdf",
    "title": "ANG HDHP 8000 8000 SOB",
    "tags": [],
    "notes": ""
  },
  {
    "file": "ANG TRAD 2000 4000 SOB.pdf",
    "title": "ANG TRAD 2000 4000 SOB",
    "tags": [],
    "notes": ""
  },
  {
    "file": "ANG_HDHP_8000_8000_16631_2025-12-22T16-03-06_SBC.pdf",
    "title": "ANG HDHP 8000 8000 16631 2025 12 22T16 03 06 SBC",
    "tags": [],
    "notes": ""
  },
  {
    "file": "ANG_TRAD_2000_4000_16630_2025-12-22T16-03-00_SBC.pdf",
    "title": "ANG TRAD 2000 4000 16630 2025 12 22T16 03 00 SBC",
    "tags": [],
    "notes": ""
  },
  {
    "file": "BCBS dental summary.pdf",
    "title": "BCBS dental summary",
    "tags": [],
    "notes": ""
  },
  {
    "file": "BCBS group_additional_dependent_form.pdf",
    "title": "BCBS group additional dependent form",
    "tags": [],
    "notes": ""
  },
  {
    "file": "BCBS group_enrollment_form.pdf",
    "title": "BCBS group enrollment form",
    "tags": [],
    "notes": ""
  },
  {
    "file": "BCBS vision summary.pdf",
    "title": "BCBS vision summary",
    "tags": [],
    "notes": ""
  },
  {
    "file": "Beneficiary Designation (LC-7829).pdf",
    "title": "Beneficiary Designation (LC 7829)",
    "tags": [],
    "notes": ""
  },
  {
    "file": "Benefit Enrollment Form 2026.pdf",
    "title": "Benefit Enrollment Form 2026",
    "tags": [],
    "notes": ""
  },
  {
    "file": "Employee Benefits Summary - 2025 - update Februray.pdf",
    "title": "Employee Benefits Summary 2025 update Februray",
    "tags": [],
    "notes": ""
  },
  {
    "file": "Employee Benefits Summary - 2026 v1.pdf",
    "title": "Employee Benefits Summary 2026 v1",
    "tags": [],
    "notes": ""
  },
  {
    "file": "EVerifyParticipationPoster.pdf",
    "title": "EVerifyParticipationPoster",
    "tags": [],
    "notes": ""
  },
  {
    "file": "Hartford Accident attending physician statement form.pdf",
    "title": "Hartford Accident attending physician statement form",
    "tags": [],
    "notes": ""
  },
  {
    "file": "Hartford Accident benefit claim guide.pdf",
    "title": "Hartford Accident benefit claim guide",
    "tags": [],
    "notes": ""
  },
  {
    "file": "Hartford Accident death benefit claim form.pdf",
    "title": "Hartford Accident death benefit claim form",
    "tags": [],
    "notes": ""
  },
  {
    "file": "Hartford Accident health screening benefit claim form.pdf",
    "title": "Hartford Accident health screening benefit claim form",
    "tags": [],
    "notes": ""
  },
  {
    "file": "Hartford Accident prevention benefit claim form.pdf",
    "title": "Hartford Accident prevention benefit claim form",
    "tags": [],
    "notes": ""
  },
  {
    "file": "Hartford Beneficiary Designation Form.pdf",
    "title": "Hartford Beneficiary Designation Form",
    "tags": [],
    "notes": ""
  },
  {
    "file": "Hartford Beneficiary Designation guide.pdf",
    "title": "Hartford Beneficiary Designation guide",
    "tags": [],
    "notes": ""
  },
  {
    "file": "Hartford Benefit Enrollment form.pdf",
    "title": "Hartford Benefit Enrollment form",
    "tags": [],
    "notes": ""
  },
  {
    "file": "HB2-SignWithNoGap-101309.pdf",
    "title": "HB2 SignWithNoGap 101309",
    "tags": [],
    "notes": ""
  },
  {
    "file": "How to Submit a Claim for Supplemental Insurance Products.pdf",
    "title": "How to Submit a Claim for Supplemental Insurance Products",
    "tags": [],
    "notes": ""
  },
  {
    "file": "How to Submit Nomination (READ FIRST).docx",
    "title": "How to Submit Nomination (READ FIRST)",
    "tags": [],
    "notes": ""
  },
  {
    "file": "i-9-paper-version.pdf",
    "title": "i 9 paper version",
    "tags": [],
    "notes": ""
  },
  {
    "file": "ncdes524_rev_1_21.pdf",
    "title": "ncdes524 rev 1 21",
    "tags": [],
    "notes": ""
  },
  {
    "file": "Org Chart.pdf",
    "title": "Org Chart",
    "tags": [],
    "notes": ""
  },
  {
    "file": "OSH-WH ENGLISH Posters (9-22).pdf",
    "title": "OSH WH ENGLISH Posters (9 22)",
    "tags": [],
    "notes": ""
  },
  {
    "file": "Performance Review and Goal Setting Form -Employe Name.pdf",
    "title": "Performance Review and Goal Setting Form Employe Name",
    "tags": [],
    "notes": ""
  },
  {
    "file": "Supplemental Insurance Products Attending Physician Statement Form.pdf",
    "title": "Supplemental Insurance Products Attending Physician Statement Form",
    "tags": [],
    "notes": ""
  },
  {
    "file": "Supplemental Insurance Products Claimant Statement.pdf",
    "title": "Supplemental Insurance Products Claimant Statement",
    "tags": [],
    "notes": ""
  },
  {
    "file": "Supplemental Insurance Products Health Screening Benefit Claim Form.pdf",
    "title": "Supplemental Insurance Products Health Screening Benefit Claim Form",
    "tags": [],
    "notes": ""
  },
  {
    "file": "Supplemental Insurance Products Insured Death Claim Form.pdf",
    "title": "Supplemental Insurance Products Insured Death Claim Form",
    "tags": [],
    "notes": ""
  },
  {
    "file": "Synoligo Biotechnologies, Inc. FSA Summary Plan Description 2025_V01.pdf..pdf",
    "title": "Synoligo Biotechnologies, Inc. FSA Summary Plan Description 2025 V01.pdf.",
    "tags": [],
    "notes": ""
  },
  {
    "file": "Synoligo Employee Handbook_11.27.23.pdf",
    "title": "Synoligo Employee Handbook 11.27.23",
    "tags": [],
    "notes": ""
  }
]